print_helpers/__init__.py
print_helpers/bprint.py
print_helpers/sprint.py
print_helpers-0.2.dist-info/METADATA
print_helpers-0.2.dist-info/WHEEL
print_helpers-0.2.dist-info/top_level.txt
print_helpers-0.2.dist-info/RECORD
