Metadata-Version: 2.1
Name: print-helpers
Version: 0.2
Summary: UNKNOWN
Home-page: UNKNOWN
Author: UNKNOWN
Author-email: UNKNOWN
License: UNKNOWN
Platform: UNKNOWN
